{
    "id": 185,
    "title": "さまよえる猶太人",
    "subtitle": null,
    "url": "https://www.aozora.gr.jp/cards/000879/card185.html",
    "authorIds": [
        879
    ],
    "monthlyRankingHistories": {
        "2009/01": {
            "rank": 229,
            "pageview": 384
        },
        "2009/02": {
            "rank": 306,
            "pageview": 261
        },
        "2010/10": {
            "rank": 371,
            "pageview": 85
        },
        "2018/12": {
            "rank": 316,
            "pageview": 428
        }
    }
}