{
    "id": 3265,
    "title": "カール・マルクスとその夫人",
    "subtitle": null,
    "url": "https://www.aozora.gr.jp/cards/000311/card3265.html",
    "authorIds": [
        311
    ],
    "monthlyRankingHistories": {
        "2009/01": {
            "rank": 397,
            "pageview": 264
        },
        "2009/02": {
            "rank": 416,
            "pageview": 210
        },
        "2009/03": {
            "rank": 460,
            "pageview": 199
        },
        "2009/06": {
            "rank": 476,
            "pageview": 208
        },
        "2009/07": {
            "rank": 413,
            "pageview": 238
        }
    }
}