{
    "id": 363,
    "title": "義血侠血",
    "subtitle": null,
    "url": "https://www.aozora.gr.jp/cards/000050/card363.html",
    "authorIds": [
        50
    ],
    "monthlyRankingHistories": {
        "2013/11": {
            "rank": 453,
            "pageview": 299
        },
        "2014/01": {
            "rank": 494,
            "pageview": 291
        },
        "2018/03": {
            "rank": 163,
            "pageview": 704
        },
        "2018/04": {
            "rank": 439,
            "pageview": 307
        },
        "2018/09": {
            "rank": 432,
            "pageview": 316
        }
    }
}