{
    "id": 40,
    "title": "歯車",
    "subtitle": null,
    "url": "https://www.aozora.gr.jp/cards/000879/card40.html",
    "authorIds": [
        879
    ],
    "monthlyRankingHistories": {
        "2009/01": {
            "rank": 147,
            "pageview": 549
        },
        "2009/02": {
            "rank": 136,
            "pageview": 513
        },
        "2009/03": {
            "rank": 132,
            "pageview": 499
        },
        "2009/04": {
            "rank": 153,
            "pageview": 431
        },
        "2009/05": {
            "rank": 195,
            "pageview": 401
        },
        "2009/06": {
            "rank": 209,
            "pageview": 384
        },
        "2009/07": {
            "rank": 183,
            "pageview": 481
        },
        "2009/08": {
            "rank": 166,
            "pageview": 456
        },
        "2009/09": {
            "rank": 162,
            "pageview": 460
        },
        "2009/10": {
            "rank": 204,
            "pageview": 467
        },
        "2009/11": {
            "rank": 208,
            "pageview": 476
        },
        "2009/12": {
            "rank": 241,
            "pageview": 418
        },
        "2010/01": {
            "rank": 196,
            "pageview": 509
        },
        "2010/02": {
            "rank": 173,
            "pageview": 417
        },
        "2010/03": {
            "rank": 95,
            "pageview": 694
        },
        "2010/04": {
            "rank": 170,
            "pageview": 412
        },
        "2010/05": {
            "rank": 184,
            "pageview": 430
        },
        "2010/06": {
            "rank": 169,
            "pageview": 489
        },
        "2010/07": {
            "rank": 154,
            "pageview": 492
        },
        "2010/08": {
            "rank": 100,
            "pageview": 696
        },
        "2010/09": {
            "rank": 159,
            "pageview": 464
        },
        "2010/10": {
            "rank": 225,
            "pageview": 108
        },
        "2010/11": {
            "rank": 138,
            "pageview": 559
        },
        "2010/12": {
            "rank": 170,
            "pageview": 427
        },
        "2011/01": {
            "rank": 164,
            "pageview": 593
        },
        "2011/02": {
            "rank": 194,
            "pageview": 438
        },
        "2011/03": {
            "rank": 188,
            "pageview": 429
        },
        "2011/04": {
            "rank": 180,
            "pageview": 436
        },
        "2011/05": {
            "rank": 179,
            "pageview": 522
        },
        "2011/06": {
            "rank": 174,
            "pageview": 496
        },
        "2011/07": {
            "rank": 135,
            "pageview": 602
        },
        "2011/08": {
            "rank": 142,
            "pageview": 613
        },
        "2011/09": {
            "rank": 190,
            "pageview": 437
        },
        "2011/10": {
            "rank": 185,
            "pageview": 503
        },
        "2011/11": {
            "rank": 180,
            "pageview": 519
        },
        "2011/12": {
            "rank": 201,
            "pageview": 444
        },
        "2012/01": {
            "rank": 185,
            "pageview": 561
        },
        "2012/02": {
            "rank": 205,
            "pageview": 466
        },
        "2012/03": {
            "rank": 249,
            "pageview": 425
        },
        "2012/04": {
            "rank": 231,
            "pageview": 381
        },
        "2012/05": {
            "rank": 186,
            "pageview": 518
        },
        "2012/06": {
            "rank": 196,
            "pageview": 492
        },
        "2012/07": {
            "rank": 172,
            "pageview": 606
        },
        "2012/08": {
            "rank": 186,
            "pageview": 533
        },
        "2012/09": {
            "rank": 183,
            "pageview": 552
        },
        "2012/10": {
            "rank": 204,
            "pageview": 518
        },
        "2012/11": {
            "rank": 190,
            "pageview": 553
        },
        "2012/12": {
            "rank": 195,
            "pageview": 535
        },
        "2013/01": {
            "rank": 171,
            "pageview": 765
        },
        "2013/02": {
            "rank": 165,
            "pageview": 665
        },
        "2013/03": {
            "rank": 201,
            "pageview": 533
        },
        "2013/04": {
            "rank": 205,
            "pageview": 482
        },
        "2013/05": {
            "rank": 192,
            "pageview": 549
        },
        "2013/06": {
            "rank": 170,
            "pageview": 616
        },
        "2013/07": {
            "rank": 185,
            "pageview": 614
        },
        "2013/08": {
            "rank": 211,
            "pageview": 556
        },
        "2013/09": {
            "rank": 216,
            "pageview": 519
        },
        "2013/10": {
            "rank": 239,
            "pageview": 524
        },
        "2013/11": {
            "rank": 227,
            "pageview": 530
        },
        "2013/12": {
            "rank": 91,
            "pageview": 1129
        },
        "2014/01": {
            "rank": 173,
            "pageview": 671
        },
        "2014/02": {
            "rank": 216,
            "pageview": 478
        },
        "2014/03": {
            "rank": 219,
            "pageview": 478
        },
        "2014/04": {
            "rank": 180,
            "pageview": 566
        },
        "2014/05": {
            "rank": 168,
            "pageview": 706
        },
        "2014/06": {
            "rank": 172,
            "pageview": 674
        },
        "2014/07": {
            "rank": 104,
            "pageview": 1135
        },
        "2014/08": {
            "rank": 181,
            "pageview": 686
        },
        "2014/09": {
            "rank": 221,
            "pageview": 523
        },
        "2014/10": {
            "rank": 159,
            "pageview": 727
        },
        "2014/11": {
            "rank": 144,
            "pageview": 845
        },
        "2015/01": {
            "rank": 136,
            "pageview": 909
        },
        "2015/02": {
            "rank": 150,
            "pageview": 680
        },
        "2015/03": {
            "rank": 160,
            "pageview": 665
        },
        "2015/04": {
            "rank": 132,
            "pageview": 787
        },
        "2015/05": {
            "rank": 156,
            "pageview": 755
        },
        "2015/06": {
            "rank": 139,
            "pageview": 910
        },
        "2015/07": {
            "rank": 106,
            "pageview": 1139
        },
        "2015/09": {
            "rank": 168,
            "pageview": 668
        },
        "2015/10": {
            "rank": 166,
            "pageview": 720
        },
        "2015/11": {
            "rank": 140,
            "pageview": 830
        },
        "2015/12": {
            "rank": 126,
            "pageview": 894
        },
        "2016/01": {
            "rank": 136,
            "pageview": 1034
        },
        "2016/02": {
            "rank": 148,
            "pageview": 802
        },
        "2016/03": {
            "rank": 139,
            "pageview": 788
        },
        "2016/04": {
            "rank": 138,
            "pageview": 800
        },
        "2016/05": {
            "rank": 116,
            "pageview": 1037
        },
        "2016/06": {
            "rank": 115,
            "pageview": 1067
        },
        "2016/07": {
            "rank": 117,
            "pageview": 1042
        },
        "2016/08": {
            "rank": 137,
            "pageview": 892
        },
        "2016/09": {
            "rank": 140,
            "pageview": 826
        },
        "2016/10": {
            "rank": 137,
            "pageview": 973
        },
        "2016/11": {
            "rank": 137,
            "pageview": 997
        },
        "2016/12": {
            "rank": 141,
            "pageview": 894
        },
        "2017/01": {
            "rank": 132,
            "pageview": 1064
        },
        "2017/02": {
            "rank": 117,
            "pageview": 1003
        },
        "2017/03": {
            "rank": 149,
            "pageview": 814
        },
        "2017/04": {
            "rank": 131,
            "pageview": 935
        },
        "2017/05": {
            "rank": 145,
            "pageview": 939
        },
        "2017/06": {
            "rank": 126,
            "pageview": 1075
        },
        "2017/07": {
            "rank": 104,
            "pageview": 1187
        },
        "2017/08": {
            "rank": 126,
            "pageview": 993
        },
        "2017/09": {
            "rank": 135,
            "pageview": 856
        },
        "2017/10": {
            "rank": 130,
            "pageview": 1024
        },
        "2017/11": {
            "rank": 119,
            "pageview": 1077
        },
        "2017/12": {
            "rank": 129,
            "pageview": 922
        },
        "2018/01": {
            "rank": 133,
            "pageview": 1023
        },
        "2018/02": {
            "rank": 134,
            "pageview": 822
        },
        "2018/03": {
            "rank": 134,
            "pageview": 834
        },
        "2018/04": {
            "rank": 125,
            "pageview": 892
        },
        "2018/05": {
            "rank": 102,
            "pageview": 1201
        },
        "2018/06": {
            "rank": 104,
            "pageview": 1250
        },
        "2018/07": {
            "rank": 109,
            "pageview": 1174
        },
        "2018/08": {
            "rank": 129,
            "pageview": 957
        },
        "2018/09": {
            "rank": 119,
            "pageview": 971
        },
        "2018/10": {
            "rank": 122,
            "pageview": 1136
        },
        "2018/11": {
            "rank": 93,
            "pageview": 1309
        },
        "2018/12": {
            "rank": 84,
            "pageview": 1296
        }
    }
}