{
    "id": 424,
    "title": "檸檬",
    "subtitle": null,
    "url": "https://www.aozora.gr.jp/cards/000074/card424.html",
    "authorIds": [
        74
    ],
    "monthlyRankingHistories": {
        "2009/01": {
            "rank": 24,
            "pageview": 2196
        },
        "2009/02": {
            "rank": 25,
            "pageview": 1740
        },
        "2009/03": {
            "rank": 21,
            "pageview": 1988
        },
        "2009/04": {
            "rank": 20,
            "pageview": 2088
        },
        "2009/05": {
            "rank": 18,
            "pageview": 2424
        },
        "2009/06": {
            "rank": 17,
            "pageview": 2731
        },
        "2009/07": {
            "rank": 31,
            "pageview": 2670
        },
        "2009/08": {
            "rank": 40,
            "pageview": 2042
        },
        "2009/09": {
            "rank": 30,
            "pageview": 2067
        },
        "2009/10": {
            "rank": 36,
            "pageview": 2108
        },
        "2009/11": {
            "rank": 34,
            "pageview": 2275
        },
        "2009/12": {
            "rank": 35,
            "pageview": 2192
        },
        "2010/01": {
            "rank": 27,
            "pageview": 2432
        },
        "2010/02": {
            "rank": 14,
            "pageview": 3295
        },
        "2010/03": {
            "rank": 21,
            "pageview": 2527
        },
        "2010/04": {
            "rank": 18,
            "pageview": 2573
        },
        "2010/05": {
            "rank": 18,
            "pageview": 3047
        },
        "2010/06": {
            "rank": 20,
            "pageview": 2750
        },
        "2010/07": {
            "rank": 20,
            "pageview": 2555
        },
        "2010/08": {
            "rank": 26,
            "pageview": 2139
        },
        "2010/09": {
            "rank": 21,
            "pageview": 2337
        },
        "2010/10": {
            "rank": 45,
            "pageview": 282
        },
        "2010/11": {
            "rank": 23,
            "pageview": 2321
        },
        "2010/12": {
            "rank": 22,
            "pageview": 1955
        },
        "2011/01": {
            "rank": 19,
            "pageview": 2720
        },
        "2011/02": {
            "rank": 20,
            "pageview": 2345
        },
        "2011/03": {
            "rank": 22,
            "pageview": 2318
        },
        "2011/04": {
            "rank": 30,
            "pageview": 2381
        },
        "2011/05": {
            "rank": 14,
            "pageview": 4067
        },
        "2011/06": {
            "rank": 14,
            "pageview": 5102
        },
        "2011/07": {
            "rank": 15,
            "pageview": 3769
        },
        "2011/08": {
            "rank": 20,
            "pageview": 3422
        },
        "2011/09": {
            "rank": 17,
            "pageview": 2956
        },
        "2011/10": {
            "rank": 20,
            "pageview": 3224
        },
        "2011/11": {
            "rank": 24,
            "pageview": 2873
        },
        "2011/12": {
            "rank": 24,
            "pageview": 2549
        },
        "2012/01": {
            "rank": 19,
            "pageview": 3291
        },
        "2012/02": {
            "rank": 20,
            "pageview": 2903
        },
        "2012/03": {
            "rank": 19,
            "pageview": 3588
        },
        "2012/04": {
            "rank": 21,
            "pageview": 2939
        },
        "2012/05": {
            "rank": 16,
            "pageview": 5199
        },
        "2012/06": {
            "rank": 19,
            "pageview": 3885
        },
        "2012/07": {
            "rank": 19,
            "pageview": 4114
        },
        "2012/08": {
            "rank": 21,
            "pageview": 3052
        },
        "2012/09": {
            "rank": 20,
            "pageview": 3315
        },
        "2012/10": {
            "rank": 18,
            "pageview": 3386
        },
        "2012/11": {
            "rank": 27,
            "pageview": 2856
        },
        "2012/12": {
            "rank": 24,
            "pageview": 2797
        },
        "2013/01": {
            "rank": 33,
            "pageview": 2921
        },
        "2013/02": {
            "rank": 29,
            "pageview": 2629
        },
        "2013/03": {
            "rank": 22,
            "pageview": 2836
        },
        "2013/04": {
            "rank": 24,
            "pageview": 2499
        },
        "2013/05": {
            "rank": 21,
            "pageview": 3277
        },
        "2013/06": {
            "rank": 12,
            "pageview": 5216
        },
        "2013/07": {
            "rank": 18,
            "pageview": 3857
        },
        "2013/08": {
            "rank": 26,
            "pageview": 2941
        },
        "2013/09": {
            "rank": 25,
            "pageview": 2673
        },
        "2013/10": {
            "rank": 25,
            "pageview": 3379
        },
        "2013/11": {
            "rank": 18,
            "pageview": 3659
        },
        "2013/12": {
            "rank": 21,
            "pageview": 3056
        },
        "2014/01": {
            "rank": 28,
            "pageview": 3625
        },
        "2014/02": {
            "rank": 21,
            "pageview": 2808
        },
        "2014/03": {
            "rank": 25,
            "pageview": 3116
        },
        "2014/04": {
            "rank": 22,
            "pageview": 3697
        },
        "2014/05": {
            "rank": 21,
            "pageview": 3955
        },
        "2014/06": {
            "rank": 20,
            "pageview": 3807
        },
        "2014/07": {
            "rank": 22,
            "pageview": 4271
        },
        "2014/08": {
            "rank": 23,
            "pageview": 3576
        },
        "2014/09": {
            "rank": 22,
            "pageview": 3298
        },
        "2014/10": {
            "rank": 26,
            "pageview": 2951
        },
        "2014/11": {
            "rank": 28,
            "pageview": 3263
        },
        "2015/01": {
            "rank": 24,
            "pageview": 3677
        },
        "2015/02": {
            "rank": 21,
            "pageview": 3315
        },
        "2015/03": {
            "rank": 21,
            "pageview": 3729
        },
        "2015/04": {
            "rank": 20,
            "pageview": 3824
        },
        "2015/05": {
            "rank": 20,
            "pageview": 5085
        },
        "2015/06": {
            "rank": 16,
            "pageview": 5914
        },
        "2015/07": {
            "rank": 15,
            "pageview": 6410
        },
        "2015/09": {
            "rank": 21,
            "pageview": 4372
        },
        "2015/10": {
            "rank": 20,
            "pageview": 4431
        },
        "2015/11": {
            "rank": 22,
            "pageview": 4617
        },
        "2015/12": {
            "rank": 18,
            "pageview": 4689
        },
        "2016/01": {
            "rank": 12,
            "pageview": 8480
        },
        "2016/02": {
            "rank": 18,
            "pageview": 4211
        },
        "2016/03": {
            "rank": 19,
            "pageview": 4099
        },
        "2016/04": {
            "rank": 20,
            "pageview": 4643
        },
        "2016/05": {
            "rank": 13,
            "pageview": 6669
        },
        "2016/06": {
            "rank": 15,
            "pageview": 6756
        },
        "2016/07": {
            "rank": 16,
            "pageview": 5920
        },
        "2016/08": {
            "rank": 18,
            "pageview": 4797
        },
        "2016/09": {
            "rank": 19,
            "pageview": 4343
        },
        "2016/10": {
            "rank": 21,
            "pageview": 4590
        },
        "2016/11": {
            "rank": 17,
            "pageview": 5220
        },
        "2016/12": {
            "rank": 24,
            "pageview": 4200
        },
        "2017/01": {
            "rank": 22,
            "pageview": 4301
        },
        "2017/02": {
            "rank": 20,
            "pageview": 3936
        },
        "2017/03": {
            "rank": 18,
            "pageview": 4686
        },
        "2017/04": {
            "rank": 20,
            "pageview": 4485
        },
        "2017/05": {
            "rank": 17,
            "pageview": 5835
        },
        "2017/06": {
            "rank": 16,
            "pageview": 6313
        },
        "2017/07": {
            "rank": 16,
            "pageview": 6336
        },
        "2017/08": {
            "rank": 17,
            "pageview": 4980
        },
        "2017/09": {
            "rank": 16,
            "pageview": 4688
        },
        "2017/10": {
            "rank": 16,
            "pageview": 6298
        },
        "2017/11": {
            "rank": 19,
            "pageview": 5262
        },
        "2017/12": {
            "rank": 17,
            "pageview": 5084
        },
        "2018/01": {
            "rank": 19,
            "pageview": 5040
        },
        "2018/02": {
            "rank": 17,
            "pageview": 4530
        },
        "2018/03": {
            "rank": 18,
            "pageview": 4917
        },
        "2018/04": {
            "rank": 16,
            "pageview": 5563
        },
        "2018/05": {
            "rank": 15,
            "pageview": 7256
        },
        "2018/06": {
            "rank": 12,
            "pageview": 7561
        },
        "2018/07": {
            "rank": 11,
            "pageview": 7733
        },
        "2018/08": {
            "rank": 18,
            "pageview": 5316
        },
        "2018/09": {
            "rank": 15,
            "pageview": 6694
        },
        "2018/10": {
            "rank": 17,
            "pageview": 5812
        },
        "2018/11": {
            "rank": 14,
            "pageview": 6732
        },
        "2018/12": {
            "rank": 11,
            "pageview": 7804
        }
    }
}