{
    "id": 43077,
    "title": "地震雑感",
    "subtitle": null,
    "url": "https://www.aozora.gr.jp/cards/000042/card43077.html",
    "authorIds": [
        42
    ],
    "monthlyRankingHistories": {
        "2011/03": {
            "rank": 230,
            "pageview": 351
        },
        "2011/04": {
            "rank": 207,
            "pageview": 382
        },
        "2011/05": {
            "rank": 455,
            "pageview": 240
        },
        "2011/06": {
            "rank": 414,
            "pageview": 229
        }
    }
}