{
    "id": 46710,
    "title": "キューピー",
    "subtitle": null,
    "url": "https://www.aozora.gr.jp/cards/000096/card46710.html",
    "authorIds": [
        96
    ],
    "monthlyRankingHistories": {
        "2017/08": {
            "rank": 459,
            "pageview": 318
        },
        "2018/02": {
            "rank": 424,
            "pageview": 308
        },
        "2018/04": {
            "rank": 483,
            "pageview": 287
        },
        "2018/09": {
            "rank": 446,
            "pageview": 310
        },
        "2018/10": {
            "rank": 495,
            "pageview": 307
        },
        "2018/11": {
            "rank": 461,
            "pageview": 325
        }
    }
}