{
    "id": 49959,
    "title": "鰻の話",
    "subtitle": null,
    "url": "https://www.aozora.gr.jp/cards/001403/card49959.html",
    "authorIds": [
        1403
    ],
    "monthlyRankingHistories": {
        "2010/10": {
            "rank": 218,
            "pageview": 111
        },
        "2011/07": {
            "rank": 263,
            "pageview": 348
        },
        "2012/07": {
            "rank": 496,
            "pageview": 246
        },
        "2012/09": {
            "rank": 500,
            "pageview": 239
        },
        "2012/10": {
            "rank": 441,
            "pageview": 266
        },
        "2012/11": {
            "rank": 462,
            "pageview": 261
        },
        "2013/07": {
            "rank": 458,
            "pageview": 296
        },
        "2014/07": {
            "rank": 406,
            "pageview": 348
        },
        "2015/07": {
            "rank": 490,
            "pageview": 296
        }
    }
}