{
    "id": 50351,
    "title": "五重塔",
    "subtitle": null,
    "url": "https://www.aozora.gr.jp/cards/000051/card50351.html",
    "authorIds": [
        51
    ],
    "monthlyRankingHistories": {
        "2009/11": {
            "rank": 165,
            "pageview": 592
        },
        "2009/12": {
            "rank": 489,
            "pageview": 239
        },
        "2010/01": {
            "rank": 458,
            "pageview": 269
        },
        "2010/02": {
            "rank": 366,
            "pageview": 237
        },
        "2010/03": {
            "rank": 417,
            "pageview": 212
        },
        "2010/04": {
            "rank": 331,
            "pageview": 240
        },
        "2010/05": {
            "rank": 412,
            "pageview": 241
        },
        "2010/06": {
            "rank": 288,
            "pageview": 309
        },
        "2010/07": {
            "rank": 389,
            "pageview": 239
        },
        "2010/08": {
            "rank": 407,
            "pageview": 223
        },
        "2010/09": {
            "rank": 273,
            "pageview": 301
        },
        "2010/11": {
            "rank": 322,
            "pageview": 283
        },
        "2010/12": {
            "rank": 276,
            "pageview": 285
        },
        "2011/01": {
            "rank": 259,
            "pageview": 408
        },
        "2011/02": {
            "rank": 282,
            "pageview": 312
        },
        "2011/03": {
            "rank": 286,
            "pageview": 289
        },
        "2011/04": {
            "rank": 292,
            "pageview": 278
        },
        "2011/05": {
            "rank": 353,
            "pageview": 286
        },
        "2011/06": {
            "rank": 454,
            "pageview": 212
        },
        "2011/08": {
            "rank": 459,
            "pageview": 225
        },
        "2011/09": {
            "rank": 372,
            "pageview": 249
        },
        "2011/10": {
            "rank": 444,
            "pageview": 231
        },
        "2011/11": {
            "rank": 471,
            "pageview": 218
        },
        "2011/12": {
            "rank": 462,
            "pageview": 223
        },
        "2012/01": {
            "rank": 398,
            "pageview": 294
        },
        "2012/02": {
            "rank": 326,
            "pageview": 302
        },
        "2012/03": {
            "rank": 269,
            "pageview": 391
        },
        "2012/04": {
            "rank": 335,
            "pageview": 292
        },
        "2012/05": {
            "rank": 252,
            "pageview": 394
        },
        "2012/06": {
            "rank": 388,
            "pageview": 279
        },
        "2012/07": {
            "rank": 441,
            "pageview": 273
        },
        "2012/08": {
            "rank": 436,
            "pageview": 257
        },
        "2012/09": {
            "rank": 458,
            "pageview": 257
        },
        "2012/10": {
            "rank": 307,
            "pageview": 365
        },
        "2012/11": {
            "rank": 408,
            "pageview": 292
        },
        "2012/12": {
            "rank": 495,
            "pageview": 236
        },
        "2013/01": {
            "rank": 475,
            "pageview": 331
        },
        "2013/02": {
            "rank": 438,
            "pageview": 288
        },
        "2013/03": {
            "rank": 500,
            "pageview": 248
        },
        "2013/05": {
            "rank": 373,
            "pageview": 317
        },
        "2013/06": {
            "rank": 360,
            "pageview": 341
        },
        "2013/08": {
            "rank": 453,
            "pageview": 285
        },
        "2014/02": {
            "rank": 416,
            "pageview": 281
        },
        "2015/03": {
            "rank": 384,
            "pageview": 307
        },
        "2015/04": {
            "rank": 436,
            "pageview": 283
        },
        "2017/01": {
            "rank": 459,
            "pageview": 330
        }
    }
}