{
    "id": 53241,
    "title": "抒情小曲集",
    "subtitle": "04 抒情小曲集",
    "url": "https://www.aozora.gr.jp/cards/001579/card53241.html",
    "authorIds": [
        1579
    ],
    "monthlyRankingHistories": {
        "2009/01": {
            "rank": null,
            "pageview": null
        },
        "2009/02": {
            "rank": null,
            "pageview": null
        },
        "2009/03": {
            "rank": null,
            "pageview": null
        },
        "2009/04": {
            "rank": null,
            "pageview": null
        },
        "2009/05": {
            "rank": null,
            "pageview": null
        },
        "2009/06": {
            "rank": null,
            "pageview": null
        },
        "2009/07": {
            "rank": null,
            "pageview": null
        },
        "2009/08": {
            "rank": null,
            "pageview": null
        },
        "2009/09": {
            "rank": null,
            "pageview": null
        },
        "2009/10": {
            "rank": null,
            "pageview": null
        },
        "2009/11": {
            "rank": null,
            "pageview": null
        },
        "2009/12": {
            "rank": null,
            "pageview": null
        },
        "2010/01": {
            "rank": null,
            "pageview": null
        },
        "2010/02": {
            "rank": null,
            "pageview": null
        },
        "2010/03": {
            "rank": null,
            "pageview": null
        },
        "2010/04": {
            "rank": null,
            "pageview": null
        },
        "2010/05": {
            "rank": null,
            "pageview": null
        },
        "2010/06": {
            "rank": null,
            "pageview": null
        },
        "2010/07": {
            "rank": null,
            "pageview": null
        },
        "2010/08": {
            "rank": null,
            "pageview": null
        },
        "2010/09": {
            "rank": null,
            "pageview": null
        },
        "2010/10": {
            "rank": null,
            "pageview": null
        },
        "2010/11": {
            "rank": null,
            "pageview": null
        },
        "2010/12": {
            "rank": null,
            "pageview": null
        },
        "2011/01": {
            "rank": null,
            "pageview": null
        },
        "2011/02": {
            "rank": null,
            "pageview": null
        },
        "2011/03": {
            "rank": null,
            "pageview": null
        },
        "2011/04": {
            "rank": null,
            "pageview": null
        },
        "2011/05": {
            "rank": null,
            "pageview": null
        },
        "2011/06": {
            "rank": null,
            "pageview": null
        },
        "2011/07": {
            "rank": null,
            "pageview": null
        },
        "2011/08": {
            "rank": null,
            "pageview": null
        },
        "2011/09": {
            "rank": null,
            "pageview": null
        },
        "2011/10": {
            "rank": null,
            "pageview": null
        },
        "2011/11": {
            "rank": null,
            "pageview": null
        },
        "2011/12": {
            "rank": null,
            "pageview": null
        },
        "2012/01": {
            "rank": null,
            "pageview": null
        },
        "2012/02": {
            "rank": null,
            "pageview": null
        },
        "2012/03": {
            "rank": null,
            "pageview": null
        },
        "2012/04": {
            "rank": null,
            "pageview": null
        },
        "2012/05": {
            "rank": null,
            "pageview": null
        },
        "2012/06": {
            "rank": null,
            "pageview": null
        },
        "2012/07": {
            "rank": null,
            "pageview": null
        },
        "2012/08": {
            "rank": null,
            "pageview": null
        },
        "2012/09": {
            "rank": null,
            "pageview": null
        },
        "2012/10": {
            "rank": null,
            "pageview": null
        },
        "2012/11": {
            "rank": null,
            "pageview": null
        },
        "2012/12": {
            "rank": null,
            "pageview": null
        },
        "2013/01": {
            "rank": 64,
            "pageview": 1696
        },
        "2013/02": {
            "rank": 286,
            "pageview": 402
        },
        "2013/03": {
            "rank": 252,
            "pageview": 439
        },
        "2013/04": {
            "rank": 226,
            "pageview": 435
        },
        "2013/05": {
            "rank": 291,
            "pageview": 387
        },
        "2013/06": {
            "rank": 269,
            "pageview": 431
        },
        "2013/07": {
            "rank": 271,
            "pageview": 445
        },
        "2013/08": {
            "rank": 313,
            "pageview": 382
        },
        "2013/09": {
            "rank": 263,
            "pageview": 439
        },
        "2013/10": {
            "rank": 237,
            "pageview": 526
        },
        "2013/11": {
            "rank": 268,
            "pageview": 456
        },
        "2013/12": {
            "rank": 313,
            "pageview": 381
        },
        "2014/01": {
            "rank": 248,
            "pageview": 498
        },
        "2014/02": {
            "rank": 237,
            "pageview": 441
        },
        "2014/03": {
            "rank": 195,
            "pageview": 505
        },
        "2014/04": {
            "rank": 209,
            "pageview": 497
        },
        "2014/05": {
            "rank": 219,
            "pageview": 547
        },
        "2014/06": {
            "rank": 175,
            "pageview": 660
        },
        "2014/07": {
            "rank": 205,
            "pageview": 622
        },
        "2014/08": {
            "rank": 209,
            "pageview": 617
        },
        "2014/09": {
            "rank": 190,
            "pageview": 613
        },
        "2014/10": {
            "rank": 209,
            "pageview": 539
        },
        "2014/11": {
            "rank": 202,
            "pageview": 611
        },
        "2015/01": {
            "rank": 203,
            "pageview": 660
        },
        "2015/02": {
            "rank": 130,
            "pageview": 743
        },
        "2015/03": {
            "rank": 114,
            "pageview": 849
        },
        "2015/04": {
            "rank": 100,
            "pageview": 978
        },
        "2015/05": {
            "rank": 100,
            "pageview": 1068
        },
        "2015/06": {
            "rank": 146,
            "pageview": 861
        },
        "2015/07": {
            "rank": 210,
            "pageview": 597
        },
        "2015/09": {
            "rank": 186,
            "pageview": 603
        },
        "2015/10": {
            "rank": 191,
            "pageview": 653
        },
        "2015/11": {
            "rank": 190,
            "pageview": 616
        },
        "2015/12": {
            "rank": 161,
            "pageview": 728
        },
        "2016/01": {
            "rank": 183,
            "pageview": 783
        },
        "2016/02": {
            "rank": 164,
            "pageview": 694
        },
        "2016/03": {
            "rank": 148,
            "pageview": 740
        },
        "2016/04": {
            "rank": 122,
            "pageview": 867
        },
        "2016/05": {
            "rank": 169,
            "pageview": 774
        },
        "2016/06": {
            "rank": 154,
            "pageview": 870
        },
        "2016/07": {
            "rank": 204,
            "pageview": 637
        },
        "2016/08": {
            "rank": 189,
            "pageview": 638
        },
        "2016/09": {
            "rank": 180,
            "pageview": 670
        },
        "2016/10": {
            "rank": 201,
            "pageview": 668
        },
        "2016/11": {
            "rank": 164,
            "pageview": 853
        },
        "2016/12": {
            "rank": 114,
            "pageview": 1024
        },
        "2017/01": {
            "rank": 159,
            "pageview": 908
        },
        "2017/02": {
            "rank": 152,
            "pageview": 780
        },
        "2017/03": {
            "rank": 121,
            "pageview": 925
        },
        "2017/04": {
            "rank": 107,
            "pageview": 1049
        },
        "2017/05": {
            "rank": 152,
            "pageview": 879
        },
        "2017/06": {
            "rank": 171,
            "pageview": 880
        },
        "2017/07": {
            "rank": 152,
            "pageview": 940
        },
        "2017/08": {
            "rank": 144,
            "pageview": 912
        },
        "2017/09": {
            "rank": 150,
            "pageview": 818
        },
        "2017/10": {
            "rank": 146,
            "pageview": 954
        },
        "2017/11": {
            "rank": 159,
            "pageview": 839
        },
        "2017/12": {
            "rank": 182,
            "pageview": 696
        },
        "2018/01": {
            "rank": 177,
            "pageview": 789
        },
        "2018/02": {
            "rank": 191,
            "pageview": 589
        },
        "2018/03": {
            "rank": 127,
            "pageview": 871
        },
        "2018/04": {
            "rank": 163,
            "pageview": 711
        },
        "2018/05": {
            "rank": 197,
            "pageview": 728
        },
        "2018/06": {
            "rank": 151,
            "pageview": 896
        },
        "2018/07": {
            "rank": 202,
            "pageview": 696
        },
        "2018/08": {
            "rank": 195,
            "pageview": 633
        },
        "2018/09": {
            "rank": 150,
            "pageview": 788
        },
        "2018/10": {
            "rank": 190,
            "pageview": 720
        },
        "2018/11": {
            "rank": 209,
            "pageview": 659
        },
        "2018/12": {
            "rank": 249,
            "pageview": 528
        }
    }
}